replicated/__init__.py
replicated/async_client.py
replicated/client.py
replicated/enums.py
replicated/exceptions.py
replicated/fingerprint.py
replicated/http_client.py
replicated/resources.py
replicated/services.py
replicated/state.py
replicated-0.1.0a2.dist-info/METADATA
replicated-0.1.0a2.dist-info/WHEEL
replicated-0.1.0a2.dist-info/top_level.txt
replicated-0.1.0a2.dist-info/RECORD
