Metadata-Version: 2.4
Name: replicated
Version: 0.1.0a2
Summary: Python SDK for Replicated customer, metrics, and instance insights
Author-email: Replicated <support@replicated.com>
License: MIT
Project-URL: Homepage, https://github.com/replicatedhq/replicated-python
Project-URL: Documentation, https://docs.replicated.com/sdk/python
Project-URL: Repository, https://github.com/replicatedhq/replicated-python
Project-URL: Bug Tracker, https://github.com/replicatedhq/replicated-python/issues
Keywords: replicated,sdk,metrics,customers
Classifier: Development Status :: 4 - Beta
Classifier: Intended Audience :: Developers
Classifier: License :: OSI Approved :: MIT License
Classifier: Operating System :: OS Independent
Classifier: Programming Language :: Python :: 3
Classifier: Programming Language :: Python :: 3.8
Classifier: Programming Language :: Python :: 3.9
Classifier: Programming Language :: Python :: 3.10
Classifier: Programming Language :: Python :: 3.11
Classifier: Programming Language :: Python :: 3.12
Classifier: Topic :: Software Development :: Libraries :: Python Modules
Requires-Python: >=3.8
Requires-Dist: httpx>=0.24.0
Requires-Dist: typing-extensions>=4.0.0
Provides-Extra: dev
Requires-Dist: pytest>=7.0.0; extra == "dev"
Requires-Dist: pytest-asyncio>=0.21.0; extra == "dev"
Requires-Dist: pytest-mock>=3.10.0; extra == "dev"
Requires-Dist: black>=23.0.0; extra == "dev"
Requires-Dist: isort>=5.12.0; extra == "dev"
Requires-Dist: mypy>=1.0.0; extra == "dev"
Requires-Dist: flake8>=6.0.0; extra == "dev"
